{
  "updated": "2026-07-23T04:29:45.635Z",
  "items": {
    "IHSG": {
      "value": 6416.053,
      "change": 3.89
    },
    "USD/IDR": {
      "value": 17885,
      "change": -0.56
    },
    "BBCA": {
      "value": 6475,
      "change": 0
    },
    "BBRI": {
      "value": 3060,
      "change": 3.03
    },
    "BMRI": {
      "value": 4440,
      "change": -0.89
    },
    "TLKM": {
      "value": 2680,
      "change": 0.75
    },
    "ASII": {
      "value": 5100,
      "change": 0
    },
    "S&P 500": {
      "value": 7498.96,
      "change": -0.97
    }
  }
}